{"tokens_lst": [{"ID": "o.1.1", "FORM": "3(asz)", "SEGM": "3(asz)[one]", "XPOSTAG": "NU", "HEAD": "_", "DEPREL": "_", "MISC": "_", "ID_NUM": "1", "BASE": "3(ac)", "SENSE": "one", "MORPH2": "N1=STEM", "EPOS": "NU", "POS": "NU", "FORM_ATF": "3(ac)", "FORM_NORM": "ac", "FORM_NORM_U": "ac", "FORM_NORM_SD": "ac", "BASE_NORM": "ac", "BASE_NORM_BD": "ac", "BASE_NORM_U": "ac", "BASE_NORM_SD": "ac"}, {"ID": "o.1.2", "FORM": "sze", "SEGM": "sze[barley]", "XPOSTAG": "N", "HEAD": "_", "DEPREL": "_", "MISC": "_", "ID_NUM": "2", "BASE": "ce", "SENSE": "barley", "MORPH2": "N1=STEM", "EPOS": "N", "POS": "N", "FORM_ATF": "ce", "FORM_NORM": "ce", "FORM_NORM_U": "ce", "FORM_NORM_SD": "ce", "BASE_NORM": "ce", "BASE_NORM_BD": "ce", "BASE_NORM_U": "ce", "BASE_NORM_SD": "ce"}, {"ID": "o.1.3", "FORM": "szuku-ra", "SEGM": "szukur[ration]-ak", "XPOSTAG": "N.GEN", "HEAD": "_", "DEPREL": "_", "MISC": "_", "ID_NUM": "3", "BASE": "cukur", "SENSE": "ration", "MORPH2": "N1=STEM.N5=GEN", "EPOS": "N", "POS": "N", "FORM_ATF": "cuku-ra", "FORM_NORM": "cukura", "FORM_NORM_U": "cukura", "FORM_NORM_SD": "cuku", "BASE_NORM": "cukur", "BASE_NORM_BD": "cukur", "BASE_NORM_U": "cukur", "BASE_NORM_SD": "cukur"}, {"ID": "o.1.4", "FORM": "gur", "SEGM": "gur[unit]", "XPOSTAG": "N", "HEAD": "_", "DEPREL": "_", "MISC": "_", "ID_NUM": "4", "BASE": "gur", "SENSE": "unit", "MORPH2": "N1=STEM", "EPOS": "N", "POS": "N", "FORM_ATF": "gur", "FORM_NORM": "gur", "FORM_NORM_U": "gur", "FORM_NORM_SD": "gur", "BASE_NORM": "gur", "BASE_NORM_BD": "gur", "BASE_NORM_U": "gur", "BASE_NORM_SD": "gur"}, {"ID": "o.2.1", "FORM": "ur-{d}szu-zi-an-dul3", "SEGM": "Urszuzi'dul[1][-ra]", "XPOSTAG": "PN.DAT-H", "HEAD": "_", "DEPREL": "_", "MISC": "_", "ID_NUM": "5", "BASE": "urcuzi'dul", "SENSE": "1", "MORPH2": "N1=NAME.N5=DAT-H", "EPOS": "PN", "POS": "N", "FORM_ATF": "ur-{d}cu-zi-an-dul3", "FORM_NORM": "urcuziandul", "FORM_NORM_U": "urcuziand\u1b5bl", "FORM_NORM_SD": "urd", "BASE_NORM": "_", "BASE_NORM_U": "_", "BASE_NORM_SD": "_", "BASE_NORM_BD": "_"}, {"ID": "o.3.1", "FORM": "3(asz)", "SEGM": "3(asz)[one]", "XPOSTAG": "NU", "HEAD": "_", "DEPREL": "_", "MISC": "_", "ID_NUM": "6", "BASE": "3(ac)", "SENSE": "one", "MORPH2": "N1=STEM", "EPOS": "NU", "POS": "NU", "FORM_ATF": "3(ac)", "FORM_NORM": "ac", "FORM_NORM_U": "ac", "FORM_NORM_SD": "ac", "BASE_NORM": "ac", "BASE_NORM_BD": "ac", "BASE_NORM_U": "ac", "BASE_NORM_SD": "ac"}, {"ID": "o.3.2", "FORM": "ARAD2-mu", "SEGM": "Aradmu[1]", "XPOSTAG": "PN", "HEAD": "Aradmu[1][-ak][-\u00f8]", "DEPREL": "PN.GEN.ABS", "MISC": "_", "ID_NUM": "7", "BASE": "aradmu", "SENSE": "1", "MORPH2": "N1=NAME", "EPOS": "PN", "POS": "N", "FORM_ATF": "_", "FORM_NORM": "_", "FORM_NORM_U": "_", "FORM_NORM_SD": "_", "BASE_NORM": "_", "BASE_NORM_U": "_", "BASE_NORM_SD": "_", "BASE_NORM_BD": "_"}, {"ID": "o.4.1", "FORM": "3(asz)", "SEGM": "3(asz)[one]", "XPOSTAG": "NU", "HEAD": "_", "DEPREL": "_", "MISC": "_", "ID_NUM": "8", "BASE": "3(ac)", "SENSE": "one", "MORPH2": "N1=STEM", "EPOS": "NU", "POS": "NU", "FORM_ATF": "3(ac)", "FORM_NORM": "ac", "FORM_NORM_U": "ac", "FORM_NORM_SD": "ac", "BASE_NORM": "ac", "BASE_NORM_BD": "ac", "BASE_NORM_U": "ac", "BASE_NORM_SD": "ac"}, {"ID": "o.4.2", "FORM": "da-da", "SEGM": "Dada[1][-ra]", "XPOSTAG": "PN.DAT-H", "HEAD": "_", "DEPREL": "_", "MISC": "_", "ID_NUM": "9", "BASE": "dada", "SENSE": "1", "MORPH2": "N1=NAME.N5=DAT-H", "EPOS": "PN", "POS": "N", "FORM_ATF": "da-da", "FORM_NORM": "dada", "FORM_NORM_U": "dada", "FORM_NORM_SD": "da", "BASE_NORM": "_", "BASE_NORM_U": "_", "BASE_NORM_SD": "_", "BASE_NORM_BD": "_"}, {"ID": "o.5.1", "FORM": "3(asz)", "SEGM": "3(asz)[one]", "XPOSTAG": "NU", "HEAD": "_", "DEPREL": "_", "MISC": "_", "ID_NUM": "10", "BASE": "3(ac)", "SENSE": "one", "MORPH2": "N1=STEM", "EPOS": "NU", "POS": "NU", "FORM_ATF": "3(ac)", "FORM_NORM": "ac", "FORM_NORM_U": "ac", "FORM_NORM_SD": "ac", "BASE_NORM": "ac", "BASE_NORM_BD": "ac", "BASE_NORM_U": "ac", "BASE_NORM_SD": "ac"}, {"ID": "o.5.2", "FORM": "ur-{d}ma-mi", "SEGM": "Urmami[1][-ra]", "XPOSTAG": "PN.DAT-H", "HEAD": "_", "DEPREL": "_", "MISC": "_", "ID_NUM": "11", "BASE": "urmami", "SENSE": "1", "MORPH2": "N1=NAME.N5=DAT-H", "EPOS": "PN", "POS": "N", "FORM_ATF": "ur-{d}ma-mi", "FORM_NORM": "urmami", "FORM_NORM_U": "urmami", "FORM_NORM_SD": "urd", "BASE_NORM": "_", "BASE_NORM_U": "_", "BASE_NORM_SD": "_", "BASE_NORM_BD": "_"}, {"ID": "o.6.1", "FORM": "2(asz)", "SEGM": "2(asz)[one]", "XPOSTAG": "NU", "HEAD": "_", "DEPREL": "_", "MISC": "_", "ID_NUM": "12", "BASE": "2(ac)", "SENSE": "one", "MORPH2": "N1=STEM", "EPOS": "NU", "POS": "NU", "FORM_ATF": "2(ac)", "FORM_NORM": "ac", "FORM_NORM_U": "ac", "FORM_NORM_SD": "ac", "BASE_NORM": "ac", "BASE_NORM_BD": "ac", "BASE_NORM_U": "ac", "BASE_NORM_SD": "ac"}, {"ID": "o.6.2", "FORM": "a-du-du", "SEGM": "Adudu[1][-ra]", "XPOSTAG": "PN.DAT-H", "HEAD": "_", "DEPREL": "_", "MISC": "_", "ID_NUM": "13", "BASE": "adudu", "SENSE": "1", "MORPH2": "N1=NAME.N5=DAT-H", "EPOS": "PN", "POS": "N", "FORM_ATF": "a-du-du", "FORM_NORM": "adudu", "FORM_NORM_U": "adudu", "FORM_NORM_SD": "a", "BASE_NORM": "_", "BASE_NORM_U": "_", "BASE_NORM_SD": "_", "BASE_NORM_BD": "_"}, {"ID": "o.7.1", "FORM": "3(asz)", "SEGM": "3(asz)[one]", "XPOSTAG": "NU", "HEAD": "_", "DEPREL": "_", "MISC": "_", "ID_NUM": "14", "BASE": "3(ac)", "SENSE": "one", "MORPH2": "N1=STEM", "EPOS": "NU", "POS": "NU", "FORM_ATF": "3(ac)", "FORM_NORM": "ac", "FORM_NORM_U": "ac", "FORM_NORM_SD": "ac", "BASE_NORM": "ac", "BASE_NORM_BD": "ac", "BASE_NORM_U": "ac", "BASE_NORM_SD": "ac"}, {"ID": "o.7.2", "FORM": "{d}szara2-ba-an-sa6", "SEGM": "Szarabansa[1][-ra]", "XPOSTAG": "PN.DAT-H", "HEAD": "_", "DEPREL": "_", "MISC": "_", "ID_NUM": "15", "BASE": "carabansa", "SENSE": "1", "MORPH2": "N1=NAME.N5=DAT-H", "EPOS": "PN", "POS": "N", "FORM_ATF": "{d}cara2-ba-an-sa6", "FORM_NORM": "carabansa", "FORM_NORM_U": "car\u03eabans\u03ee", "FORM_NORM_SD": "dcara", "BASE_NORM": "_", "BASE_NORM_U": "_", "BASE_NORM_SD": "_", "BASE_NORM_BD": "_"}, {"ID": "o.8.1", "FORM": "2(asz)", "SEGM": "2(asz)[one]", "XPOSTAG": "NU", "HEAD": "_", "DEPREL": "_", "MISC": "_", "ID_NUM": "16", "BASE": "2(ac)", "SENSE": "one", "MORPH2": "N1=STEM", "EPOS": "NU", "POS": "NU", "FORM_ATF": "2(ac)", "FORM_NORM": "ac", "FORM_NORM_U": "ac", "FORM_NORM_SD": "ac", "BASE_NORM": "ac", "BASE_NORM_BD": "ac", "BASE_NORM_U": "ac", "BASE_NORM_SD": "ac"}, {"ID": "o.8.2", "FORM": "ur-KU-x", "SEGM": "UrKUx[1][-ra]", "XPOSTAG": "PN.DAT-H", "HEAD": "_", "DEPREL": "_", "MISC": "_", "ID_NUM": "17", "BASE": "urkux", "SENSE": "1", "MORPH2": "N1=NAME.N5=DAT-H", "EPOS": "PN", "POS": "N", "FORM_ATF": "_", "FORM_NORM": "_", "FORM_NORM_U": "_", "FORM_NORM_SD": "_", "BASE_NORM": "_", "BASE_NORM_U": "_", "BASE_NORM_SD": "_", "BASE_NORM_BD": "_"}, {"ID": "o.9.1", "FORM": "3(asz)", "SEGM": "3(asz)[one]", "XPOSTAG": "NU", "HEAD": "_", "DEPREL": "_", "MISC": "_", "ID_NUM": "18", "BASE": "3(ac)", "SENSE": "one", "MORPH2": "N1=STEM", "EPOS": "NU", "POS": "NU", "FORM_ATF": "3(ac)", "FORM_NORM": "ac", "FORM_NORM_U": "ac", "FORM_NORM_SD": "ac", "BASE_NORM": "ac", "BASE_NORM_BD": "ac", "BASE_NORM_U": "ac", "BASE_NORM_SD": "ac"}, {"ID": "o.9.2", "FORM": "en-ra-kal", "SEGM": "Enrakal[1][-ra]", "XPOSTAG": "PN.DAT-H", "HEAD": "_", "DEPREL": "_", "MISC": "_", "ID_NUM": "19", "BASE": "enrakal", "SENSE": "1", "MORPH2": "N1=NAME.N5=DAT-H", "EPOS": "PN", "POS": "N", "FORM_ATF": "en-ra-kal", "FORM_NORM": "enrakal", "FORM_NORM_U": "enrakal", "FORM_NORM_SD": "en", "BASE_NORM": "_", "BASE_NORM_U": "_", "BASE_NORM_SD": "_", "BASE_NORM_BD": "_"}, {"ID": "o.10.1", "FORM": "3(asz)", "SEGM": "3(asz)[one]", "XPOSTAG": "NU", "HEAD": "_", "DEPREL": "_", "MISC": "_", "ID_NUM": "20", "BASE": "3(ac)", "SENSE": "one", "MORPH2": "N1=STEM", "EPOS": "NU", "POS": "NU", "FORM_ATF": "3(ac)", "FORM_NORM": "ac", "FORM_NORM_U": "ac", "FORM_NORM_SD": "ac", "BASE_NORM": "ac", "BASE_NORM_BD": "ac", "BASE_NORM_U": "ac", "BASE_NORM_SD": "ac"}, {"ID": "o.10.2", "FORM": "ur-{d}szul-pa-e3", "SEGM": "Urszulpa'e[1][-ra]", "XPOSTAG": "PN.DAT-H", "HEAD": "_", "DEPREL": "_", "MISC": "_", "ID_NUM": "21", "BASE": "urculpa'e", "SENSE": "1", "MORPH2": "N1=NAME.N5=DAT-H", "EPOS": "PN", "POS": "N", "FORM_ATF": "ur-{d}cul-pa-e3", "FORM_NORM": "urculpae", "FORM_NORM_U": "urculpa\u0bbb", "FORM_NORM_SD": "urd", "BASE_NORM": "_", "BASE_NORM_U": "_", "BASE_NORM_SD": "_", "BASE_NORM_BD": "_"}, {"ID": "o.11.1", "FORM": "2(asz)", "SEGM": "2(asz)[one]", "XPOSTAG": "NU", "HEAD": "_", "DEPREL": "_", "MISC": "_", "ID_NUM": "22", "BASE": "2(ac)", "SENSE": "one", "MORPH2": "N1=STEM", "EPOS": "NU", "POS": "NU", "FORM_ATF": "2(ac)", "FORM_NORM": "ac", "FORM_NORM_U": "ac", "FORM_NORM_SD": "ac", "BASE_NORM": "ac", "BASE_NORM_BD": "ac", "BASE_NORM_U": "ac", "BASE_NORM_SD": "ac"}, {"ID": "o.11.2", "FORM": "ur-e11-e", "SEGM": "Ure'e[1][-ra]", "XPOSTAG": "PN.DAT-H", "HEAD": "_", "DEPREL": "_", "MISC": "_", "ID_NUM": "23", "BASE": "ure'e", "SENSE": "1", "MORPH2": "N1=NAME.N5=DAT-H", "EPOS": "PN", "POS": "N", "FORM_ATF": "ur-e11-e", "FORM_NORM": "ure", "FORM_NORM_U": "ur\u0bc3", "FORM_NORM_SD": "ur", "BASE_NORM": "_", "BASE_NORM_U": "_", "BASE_NORM_SD": "_", "BASE_NORM_BD": "_"}, {"ID": "o.12.1", "FORM": "3(asz)", "SEGM": "3(asz)[one]", "XPOSTAG": "NU", "HEAD": "_", "DEPREL": "_", "MISC": "_", "ID_NUM": "24", "BASE": "3(ac)", "SENSE": "one", "MORPH2": "N1=STEM", "EPOS": "NU", "POS": "NU", "FORM_ATF": "3(ac)", "FORM_NORM": "ac", "FORM_NORM_U": "ac", "FORM_NORM_SD": "ac", "BASE_NORM": "ac", "BASE_NORM_BD": "ac", "BASE_NORM_U": "ac", "BASE_NORM_SD": "ac"}, {"ID": "o.12.2", "FORM": "ur-e11-e", "SEGM": "Ure'e[1][-ra]", "XPOSTAG": "PN.DAT-H", "HEAD": "_", "DEPREL": "_", "MISC": "_", "ID_NUM": "25", "BASE": "ure'e", "SENSE": "1", "MORPH2": "N1=NAME.N5=DAT-H", "EPOS": "PN", "POS": "N", "FORM_ATF": "ur-e11-e", "FORM_NORM": "ure", "FORM_NORM_U": "ur\u0bc3", "FORM_NORM_SD": "ur", "BASE_NORM": "_", "BASE_NORM_U": "_", "BASE_NORM_SD": "_", "BASE_NORM_BD": "_"}, {"ID": "o.12.3", "FORM": "Min-kam", "SEGM": "min[two]-ak-am", "XPOSTAG": "NU.GEN.COP-3-SG", "HEAD": "_", "DEPREL": "_", "MISC": "_", "ID_NUM": "26", "BASE": "min", "SENSE": "two", "MORPH2": "N1=STEM.N5=GEN.N6=COP-3-SG", "EPOS": "NU", "POS": "NU", "FORM_ATF": "_", "FORM_NORM": "_", "FORM_NORM_U": "_", "FORM_NORM_SD": "_", "BASE_NORM": "min", "BASE_NORM_BD": "_", "BASE_NORM_U": "min", "BASE_NORM_SD": "min"}, {"ID": "o.13.1", "FORM": "1(asz)", "SEGM": "1(asz)[one]", "XPOSTAG": "NU", "HEAD": "_", "DEPREL": "_", "MISC": "_", "ID_NUM": "27", "BASE": "1(ac)", "SENSE": "one", "MORPH2": "N1=STEM", "EPOS": "NU", "POS": "NU", "FORM_ATF": "1(ac)", "FORM_NORM": "ac", "FORM_NORM_U": "ac", "FORM_NORM_SD": "ac", "BASE_NORM": "ac", "BASE_NORM_BD": "ac", "BASE_NORM_U": "ac", "BASE_NORM_SD": "ac"}, {"ID": "o.13.2", "FORM": "1(barig)", "SEGM": "1(bariga)[unit]", "XPOSTAG": "N", "HEAD": "1(bariga)[unit]", "DEPREL": "NU", "MISC": "_", "ID_NUM": "28", "BASE": "1(bariga)", "SENSE": "unit", "MORPH2": "N1=STEM", "EPOS": "N", "POS": "N", "FORM_ATF": "1(barig)", "FORM_NORM": "1(barig)", "FORM_NORM_U": "1(barig)", "FORM_NORM_SD": "1(barig)", "BASE_NORM": "1(bariga)", "BASE_NORM_BD": "1(bariga)", "BASE_NORM_U": "1(bariga)", "BASE_NORM_SD": "1(bariga)"}, {"ID": "o.13.3", "FORM": "{d}szara2-i3-x", "SEGM": "Szara'ix[1][-ra]", "XPOSTAG": "PN.DAT-H", "HEAD": "_", "DEPREL": "_", "MISC": "_", "ID_NUM": "29", "BASE": "cara'ix", "SENSE": "1", "MORPH2": "N1=NAME.N5=DAT-H", "EPOS": "PN", "POS": "N", "FORM_ATF": "_", "FORM_NORM": "_", "FORM_NORM_U": "_", "FORM_NORM_SD": "_", "BASE_NORM": "_", "BASE_NORM_U": "_", "BASE_NORM_SD": "_", "BASE_NORM_BD": "_"}, {"ID": "o.14.1", "FORM": "3(asz)", "SEGM": "3(asz)[one]", "XPOSTAG": "NU", "HEAD": "_", "DEPREL": "_", "MISC": "_", "ID_NUM": "30", "BASE": "3(ac)", "SENSE": "one", "MORPH2": "N1=STEM", "EPOS": "NU", "POS": "NU", "FORM_ATF": "3(ac)", "FORM_NORM": "ac", "FORM_NORM_U": "ac", "FORM_NORM_SD": "ac", "BASE_NORM": "ac", "BASE_NORM_BD": "ac", "BASE_NORM_U": "ac", "BASE_NORM_SD": "ac"}, {"ID": "o.14.2", "FORM": "x-{d}x-x", "SEGM": "[1][-ra]", "XPOSTAG": "PN.DAT-H", "HEAD": "_", "DEPREL": "_", "MISC": "_", "ID_NUM": "31", "BASE": "", "SENSE": "1", "MORPH2": "N1=NAME.N5=DAT-H", "EPOS": "PN", "POS": "N", "FORM_ATF": "_", "FORM_NORM": "_", "FORM_NORM_U": "_", "FORM_NORM_SD": "_", "BASE_NORM": "_", "BASE_NORM_BD": "_", "BASE_NORM_U": "_", "BASE_NORM_SD": "_"}, {"ID": "r.1.1", "FORM": "3(asz)", "SEGM": "3(asz)[one]", "XPOSTAG": "NU", "HEAD": "_", "DEPREL": "_", "MISC": "_", "ID_NUM": "32", "BASE": "3(ac)", "SENSE": "one", "MORPH2": "N1=STEM", "EPOS": "NU", "POS": "NU", "FORM_ATF": "3(ac)", "FORM_NORM": "ac", "FORM_NORM_U": "ac", "FORM_NORM_SD": "ac", "BASE_NORM": "ac", "BASE_NORM_BD": "ac", "BASE_NORM_U": "ac", "BASE_NORM_SD": "ac"}, {"ID": "r.1.2", "FORM": "x", "SEGM": "_", "XPOSTAG": "_", "HEAD": "_", "DEPREL": "_", "MISC": "_", "ID_NUM": "33", "SENSE": "_", "BASE": "_", "EPOS": "_", "POS": "_", "FORM_ATF": "_", "FORM_NORM": "_", "FORM_NORM_U": "_", "FORM_NORM_SD": "_", "BASE_NORM": "_", "BASE_NORM_U": "_", "BASE_NORM_SD": "_", "BASE_NORM_BD": "_"}, {"ID": "r.1.3", "FORM": "x", "SEGM": "_", "XPOSTAG": "_", "HEAD": "_", "DEPREL": "_", "MISC": "_", "ID_NUM": "34", "SENSE": "_", "BASE": "_", "EPOS": "_", "POS": "_", "FORM_ATF": "_", "FORM_NORM": "_", "FORM_NORM_U": "_", "FORM_NORM_SD": "_", "BASE_NORM": "_", "BASE_NORM_U": "_", "BASE_NORM_SD": "_", "BASE_NORM_BD": "_"}, {"ID": "r.1.4", "FORM": "x", "SEGM": "_", "XPOSTAG": "_", "HEAD": "_", "DEPREL": "_", "MISC": "_", "ID_NUM": "35", "SENSE": "_", "BASE": "_", "EPOS": "_", "POS": "_", "FORM_ATF": "_", "FORM_NORM": "_", "FORM_NORM_U": "_", "FORM_NORM_SD": "_", "BASE_NORM": "_", "BASE_NORM_U": "_", "BASE_NORM_SD": "_", "BASE_NORM_BD": "_"}, {"ID": "r.2.1", "FORM": "sze", "SEGM": "sze[barley]", "XPOSTAG": "N", "HEAD": "_", "DEPREL": "_", "MISC": "_", "ID_NUM": "36", "BASE": "ce", "SENSE": "barley", "MORPH2": "N1=STEM", "EPOS": "N", "POS": "N", "FORM_ATF": "ce", "FORM_NORM": "ce", "FORM_NORM_U": "ce", "FORM_NORM_SD": "ce", "BASE_NORM": "ce", "BASE_NORM_BD": "ce", "BASE_NORM_U": "ce", "BASE_NORM_SD": "ce"}, {"ID": "r.2.2", "FORM": "szuku", "SEGM": "szukur[ration]", "XPOSTAG": "N.ABS", "HEAD": "_", "DEPREL": "_", "MISC": "_", "ID_NUM": "37", "BASE": "cukur", "SENSE": "ration", "MORPH2": "N1=STEM.N5=ABS", "EPOS": "N", "POS": "N", "FORM_ATF": "cuku", "FORM_NORM": "cuku", "FORM_NORM_U": "cuku", "FORM_NORM_SD": "cuku", "BASE_NORM": "cukur", "BASE_NORM_BD": "cukur", "BASE_NORM_U": "cukur", "BASE_NORM_SD": "cukur"}, {"ID": "r.2.3", "FORM": "e-tak4-a", "SEGM": "i[-b]-taka[abandon][-\u00f8]-a FIN.3-NH.V.3-SG-P.SUB", "XPOSTAG": "_", "HEAD": "_", "DEPREL": "_", "MISC": "_", "ID_NUM": "38", "BASE": "taka", "SENSE": "abandon", "EPOS": "_", "POS": "_", "FORM_ATF": "e-tak4-a", "FORM_NORM": "etaka", "FORM_NORM_U": "et\u03ecka", "FORM_NORM_SD": "e", "BASE_NORM": "taka", "BASE_NORM_BD": "taka", "BASE_NORM_U": "taka", "BASE_NORM_SD": "taka"}, {"ID": "r.3.1", "FORM": "2(barig)", "SEGM": "2(barig)[unit]", "XPOSTAG": "N", "HEAD": "2(bariga)[unit]", "DEPREL": "N", "MISC": "_", "ID_NUM": "39", "BASE": "2(barig)", "SENSE": "unit", "MORPH2": "N1=STEM", "EPOS": "N", "POS": "N", "FORM_ATF": "2(barig)", "FORM_NORM": "2(barig)", "FORM_NORM_U": "2(barig)", "FORM_NORM_SD": "2(barig)", "BASE_NORM": "2(barig)", "BASE_NORM_BD": "2(barig)", "BASE_NORM_U": "2(barig)", "BASE_NORM_SD": "2(barig)"}, {"ID": "r.3.2", "FORM": "lugal-za3-ge-si", "SEGM": "Lugalzagesi[1]", "XPOSTAG": "PN", "HEAD": "_", "DEPREL": "_", "MISC": "_", "ID_NUM": "40", "BASE": "lugalzagesi", "SENSE": "1", "MORPH2": "N1=NAME", "EPOS": "PN", "POS": "N", "FORM_ATF": "lugal-za3-ge-si", "FORM_NORM": "lugalzagesi", "FORM_NORM_U": "lugalz\u03ebgesi", "FORM_NORM_SD": "lugal", "BASE_NORM": "_", "BASE_NORM_U": "_", "BASE_NORM_SD": "_", "BASE_NORM_BD": "_"}, {"ID": "r.3.3", "FORM": "engar", "SEGM": "engar[farmer][-ra]", "XPOSTAG": "N.DAT-H", "HEAD": "_", "DEPREL": "_", "MISC": "_", "ID_NUM": "41", "BASE": "engar", "SENSE": "farmer", "MORPH2": "N1=STEM.N5=DAT-H", "EPOS": "N", "POS": "N", "FORM_ATF": "engar", "FORM_NORM": "engar", "FORM_NORM_U": "engar", "FORM_NORM_SD": "engar", "BASE_NORM": "engar", "BASE_NORM_BD": "engar", "BASE_NORM_U": "engar", "BASE_NORM_SD": "engar"}, {"ID": "r.4.1", "FORM": "2(barig)", "SEGM": "2(barig)[unit]", "XPOSTAG": "N", "HEAD": "2(bariga)[unit]", "DEPREL": "N", "MISC": "_", "ID_NUM": "42", "BASE": "2(barig)", "SENSE": "unit", "MORPH2": "N1=STEM", "EPOS": "N", "POS": "N", "FORM_ATF": "2(barig)", "FORM_NORM": "2(barig)", "FORM_NORM_U": "2(barig)", "FORM_NORM_SD": "2(barig)", "BASE_NORM": "2(barig)", "BASE_NORM_BD": "2(barig)", "BASE_NORM_U": "2(barig)", "BASE_NORM_SD": "2(barig)"}, {"ID": "r.4.2", "FORM": "ur-saga-mu", "SEGM": "Ursagamu[1]", "XPOSTAG": "PN", "HEAD": "_", "DEPREL": "_", "MISC": "_", "ID_NUM": "43", "BASE": "ursagamu", "SENSE": "1", "MORPH2": "N1=NAME", "EPOS": "PN", "POS": "N", "FORM_ATF": "ur-saga-mu", "FORM_NORM": "ursagamu", "FORM_NORM_U": "ursagamu", "FORM_NORM_SD": "ur", "BASE_NORM": "_", "BASE_NORM_U": "_", "BASE_NORM_SD": "_", "BASE_NORM_BD": "_"}, {"ID": "r.4.3", "FORM": "engar", "SEGM": "engar[farmer][-ra]", "XPOSTAG": "N.DAT-H", "HEAD": "_", "DEPREL": "_", "MISC": "_", "ID_NUM": "44", "BASE": "engar", "SENSE": "farmer", "MORPH2": "N1=STEM.N5=DAT-H", "EPOS": "N", "POS": "N", "FORM_ATF": "engar", "FORM_NORM": "engar", "FORM_NORM_U": "engar", "FORM_NORM_SD": "engar", "BASE_NORM": "engar", "BASE_NORM_BD": "engar", "BASE_NORM_U": "engar", "BASE_NORM_SD": "engar"}, {"ID": "r.5.1", "FORM": "2(barig)", "SEGM": "2(barig)[unit]", "XPOSTAG": "N", "HEAD": "2(bariga)[unit]", "DEPREL": "N", "MISC": "_", "ID_NUM": "45", "BASE": "2(barig)", "SENSE": "unit", "MORPH2": "N1=STEM", "EPOS": "N", "POS": "N", "FORM_ATF": "2(barig)", "FORM_NORM": "2(barig)", "FORM_NORM_U": "2(barig)", "FORM_NORM_SD": "2(barig)", "BASE_NORM": "2(barig)", "BASE_NORM_BD": "2(barig)", "BASE_NORM_U": "2(barig)", "BASE_NORM_SD": "2(barig)"}, {"ID": "r.5.2", "FORM": "ur-am3-ma", "SEGM": "Uramma[1][-ra]", "XPOSTAG": "PN.DAT-H", "HEAD": "Uramma[1][-ak]", "DEPREL": "PN.GEN", "MISC": "_", "ID_NUM": "46", "BASE": "uramma", "SENSE": "1", "MORPH2": "N1=NAME.N5=DAT-H", "EPOS": "PN", "POS": "N", "FORM_ATF": "ur-am3-ma", "FORM_NORM": "urama", "FORM_NORM_U": "ur\u03ebma", "FORM_NORM_SD": "ur", "BASE_NORM": "_", "BASE_NORM_U": "_", "BASE_NORM_SD": "_", "BASE_NORM_BD": "_"}, {"ID": "r.6.1", "FORM": "2(barig)", "SEGM": "2(barig)[unit]", "XPOSTAG": "N", "HEAD": "2(bariga)[unit]", "DEPREL": "N", "MISC": "_", "ID_NUM": "47", "BASE": "2(barig)", "SENSE": "unit", "MORPH2": "N1=STEM", "EPOS": "N", "POS": "N", "FORM_ATF": "2(barig)", "FORM_NORM": "2(barig)", "FORM_NORM_U": "2(barig)", "FORM_NORM_SD": "2(barig)", "BASE_NORM": "2(barig)", "BASE_NORM_BD": "2(barig)", "BASE_NORM_U": "2(barig)", "BASE_NORM_SD": "2(barig)"}, {"ID": "r.6.2", "FORM": "lugal-sa6-i3-zu", "SEGM": "Lugalsa'izu[1]", "XPOSTAG": "PN", "HEAD": "_", "DEPREL": "_", "MISC": "_", "ID_NUM": "48", "BASE": "lugalsa'izu", "SENSE": "1", "MORPH2": "N1=NAME", "EPOS": "PN", "POS": "N", "FORM_ATF": "lugal-sa6-i3-zu", "FORM_NORM": "lugalsaizu", "FORM_NORM_U": "lugals\u03ee\u138bzu", "FORM_NORM_SD": "lugal", "BASE_NORM": "_", "BASE_NORM_U": "_", "BASE_NORM_SD": "_", "BASE_NORM_BD": "_"}, {"ID": "r.6.3", "FORM": "engar", "SEGM": "engar[farmer][-ra]", "XPOSTAG": "N.DAT-H", "HEAD": "_", "DEPREL": "_", "MISC": "_", "ID_NUM": "49", "BASE": "engar", "SENSE": "farmer", "MORPH2": "N1=STEM.N5=DAT-H", "EPOS": "N", "POS": "N", "FORM_ATF": "engar", "FORM_NORM": "engar", "FORM_NORM_U": "engar", "FORM_NORM_SD": "engar", "BASE_NORM": "engar", "BASE_NORM_BD": "engar", "BASE_NORM_U": "engar", "BASE_NORM_SD": "engar"}, {"ID": "r.7.1", "FORM": "2(barig)", "SEGM": "2(barig)[unit]", "XPOSTAG": "N", "HEAD": "2(bariga)[unit]", "DEPREL": "N", "MISC": "_", "ID_NUM": "50", "BASE": "2(barig)", "SENSE": "unit", "MORPH2": "N1=STEM", "EPOS": "N", "POS": "N", "FORM_ATF": "2(barig)", "FORM_NORM": "2(barig)", "FORM_NORM_U": "2(barig)", "FORM_NORM_SD": "2(barig)", "BASE_NORM": "2(barig)", "BASE_NORM_BD": "2(barig)", "BASE_NORM_U": "2(barig)", "BASE_NORM_SD": "2(barig)"}, {"ID": "r.7.2", "FORM": "ur-{d}suen", "SEGM": "Ursuen[1]", "XPOSTAG": "PN", "HEAD": "_", "DEPREL": "_", "MISC": "_", "ID_NUM": "51", "BASE": "ursuen", "SENSE": "1", "MORPH2": "N1=NAME", "EPOS": "PN", "POS": "N", "FORM_ATF": "ur-{d}suen", "FORM_NORM": "ursuen", "FORM_NORM_U": "ursuen", "FORM_NORM_SD": "urd", "BASE_NORM": "_", "BASE_NORM_U": "_", "BASE_NORM_SD": "_", "BASE_NORM_BD": "_"}, {"ID": "r.7.3", "FORM": "engar", "SEGM": "engar[farmer][-ra]", "XPOSTAG": "N.DAT-H", "HEAD": "_", "DEPREL": "_", "MISC": "_", "ID_NUM": "52", "BASE": "engar", "SENSE": "farmer", "MORPH2": "N1=STEM.N5=DAT-H", "EPOS": "N", "POS": "N", "FORM_ATF": "engar", "FORM_NORM": "engar", "FORM_NORM_U": "engar", "FORM_NORM_SD": "engar", "BASE_NORM": "engar", "BASE_NORM_BD": "engar", "BASE_NORM_U": "engar", "BASE_NORM_SD": "engar"}, {"ID": "r.8.1", "FORM": "engar", "SEGM": "engar[farmer]", "XPOSTAG": "N", "HEAD": "_", "DEPREL": "_", "MISC": "_", "ID_NUM": "53", "BASE": "engar", "SENSE": "farmer", "MORPH2": "N1=STEM", "EPOS": "N", "POS": "N", "FORM_ATF": "engar", "FORM_NORM": "engar", "FORM_NORM_U": "engar", "FORM_NORM_SD": "engar", "BASE_NORM": "engar", "BASE_NORM_BD": "engar", "BASE_NORM_U": "engar", "BASE_NORM_SD": "engar"}, {"ID": "r.8.2", "FORM": "szuku", "SEGM": "szukur[ration]", "XPOSTAG": "N", "HEAD": "_", "DEPREL": "_", "MISC": "_", "ID_NUM": "54", "BASE": "cukur", "SENSE": "ration", "MORPH2": "N1=STEM", "EPOS": "N", "POS": "N", "FORM_ATF": "cuku", "FORM_NORM": "cuku", "FORM_NORM_U": "cuku", "FORM_NORM_SD": "cuku", "BASE_NORM": "cukur", "BASE_NORM_BD": "cukur", "BASE_NORM_U": "cukur", "BASE_NORM_SD": "cukur"}, {"ID": "r.8.3", "FORM": "su3", "SEGM": "sug[empty][-\u00f8][-ak]", "XPOSTAG": "NF.V.ABS.GEN", "HEAD": "_", "DEPREL": "_", "MISC": "_", "ID_NUM": "55", "BASE": "sug", "SENSE": "empty", "MORPH2": "NV2=STEM.N5=ABS.N5=GEN", "EPOS": "V", "POS": "V", "FORM_ATF": "su3", "FORM_NORM": "su", "FORM_NORM_U": "s\u1b5b", "FORM_NORM_SD": "su", "BASE_NORM": "sug", "BASE_NORM_BD": "sug", "BASE_NORM_U": "sug", "BASE_NORM_SD": "sug"}, {"ID": "r.8.4", "FORM": "sze", "SEGM": "sze[barley][-\u00f8]", "XPOSTAG": "N.ABS", "HEAD": "_", "DEPREL": "_", "MISC": "_", "ID_NUM": "56", "BASE": "ce", "SENSE": "barley", "MORPH2": "N1=STEM.N5=ABS", "EPOS": "N", "POS": "N", "FORM_ATF": "ce", "FORM_NORM": "ce", "FORM_NORM_U": "ce", "FORM_NORM_SD": "ce", "BASE_NORM": "ce", "BASE_NORM_BD": "ce", "BASE_NORM_U": "ce", "BASE_NORM_SD": "ce"}, {"ID": "r.8.5", "FORM": "nu-tuku-me", "SEGM": "nu-tuku[acquire][-\u00f8]-mesz", "XPOSTAG": "NEG.NF.V.ABS.COP-3-PL", "HEAD": "_", "DEPREL": "_", "MISC": "_", "ID_NUM": "57", "BASE": "tuku", "SENSE": "acquire", "MORPH2": "NV2=STEM.NV2=STEM.N5=ABS.N6=COP-3-PL", "EPOS": "V", "POS": "V", "FORM_ATF": "nu-tuku-me", "FORM_NORM": "nutukume", "FORM_NORM_U": "nutukume", "FORM_NORM_SD": "nu", "BASE_NORM": "tuku", "BASE_NORM_BD": "tuku", "BASE_NORM_U": "tuku", "BASE_NORM_SD": "tuku"}, {"ID": "r.9.1", "FORM": "szunigin", "SEGM": "szunigin[total]", "XPOSTAG": "N", "HEAD": "_", "DEPREL": "_", "MISC": "_", "ID_NUM": "58", "BASE": "cunigin", "SENSE": "total", "MORPH2": "N1=STEM", "EPOS": "N", "POS": "N", "FORM_ATF": "cunigin", "FORM_NORM": "cunigin", "FORM_NORM_U": "cunigin", "FORM_NORM_SD": "cunigin", "BASE_NORM": "cunigin", "BASE_NORM_BD": "cunigin", "BASE_NORM_U": "cunigin", "BASE_NORM_SD": "cunigin"}, {"ID": "r.9.2", "FORM": "3(u)", "SEGM": "3(u)[ten]", "XPOSTAG": "NU", "HEAD": "_", "DEPREL": "_", "MISC": "_", "ID_NUM": "59", "BASE": "3(u)", "SENSE": "ten", "MORPH2": "N1=STEM", "EPOS": "NU", "POS": "NU", "FORM_ATF": "3(u)", "FORM_NORM": "u", "FORM_NORM_U": "u", "FORM_NORM_SD": "u", "BASE_NORM": "u", "BASE_NORM_BD": "u", "BASE_NORM_U": "u", "BASE_NORM_SD": "u"}, {"ID": "r.9.3", "FORM": "9(asz)", "SEGM": "9(asz)[one]", "XPOSTAG": "NU", "HEAD": "_", "DEPREL": "_", "MISC": "_", "ID_NUM": "60", "BASE": "9(ac)", "SENSE": "one", "MORPH2": "N1=STEM", "EPOS": "NU", "POS": "NU", "FORM_ATF": "9(ac)", "FORM_NORM": "9", "FORM_NORM_U": "9", "FORM_NORM_SD": "9", "BASE_NORM": "9", "BASE_NORM_BD": "9", "BASE_NORM_U": "9", "BASE_NORM_SD": "9"}, {"ID": "r.9.4", "FORM": "1(barig)", "SEGM": "1(bariga)[unit]", "XPOSTAG": "N", "HEAD": "1(bariga)[unit]", "DEPREL": "NU", "MISC": "_", "ID_NUM": "61", "BASE": "1(bariga)", "SENSE": "unit", "MORPH2": "N1=STEM", "EPOS": "N", "POS": "N", "FORM_ATF": "1(barig)", "FORM_NORM": "1(barig)", "FORM_NORM_U": "1(barig)", "FORM_NORM_SD": "1(barig)", "BASE_NORM": "1(bariga)", "BASE_NORM_BD": "1(bariga)", "BASE_NORM_U": "1(bariga)", "BASE_NORM_SD": "1(bariga)"}, {"ID": "r.9.5", "FORM": "sze", "SEGM": "sze[barley]", "XPOSTAG": "N", "HEAD": "_", "DEPREL": "_", "MISC": "_", "ID_NUM": "62", "BASE": "ce", "SENSE": "barley", "MORPH2": "N1=STEM", "EPOS": "N", "POS": "N", "FORM_ATF": "ce", "FORM_NORM": "ce", "FORM_NORM_U": "ce", "FORM_NORM_SD": "ce", "BASE_NORM": "ce", "BASE_NORM_BD": "ce", "BASE_NORM_U": "ce", "BASE_NORM_SD": "ce"}, {"ID": "r.9.6", "FORM": "szuku-ra", "SEGM": "szukur[ration]-ak", "XPOSTAG": "N.GEN", "HEAD": "_", "DEPREL": "_", "MISC": "_", "ID_NUM": "63", "BASE": "cukur", "SENSE": "ration", "MORPH2": "N1=STEM.N5=GEN", "EPOS": "N", "POS": "N", "FORM_ATF": "cuku-ra", "FORM_NORM": "cukura", "FORM_NORM_U": "cukura", "FORM_NORM_SD": "cuku", "BASE_NORM": "cukur", "BASE_NORM_BD": "cukur", "BASE_NORM_U": "cukur", "BASE_NORM_SD": "cukur"}, {"ID": "r.9.7", "FORM": "gur", "SEGM": "gur[unit]", "XPOSTAG": "N", "HEAD": "_", "DEPREL": "_", "MISC": "_", "ID_NUM": "64", "BASE": "gur", "SENSE": "unit", "MORPH2": "N1=STEM", "EPOS": "N", "POS": "N", "FORM_ATF": "gur", "FORM_NORM": "gur", "FORM_NORM_U": "gur", "FORM_NORM_SD": "gur", "BASE_NORM": "gur", "BASE_NORM_BD": "gur", "BASE_NORM_U": "gur", "BASE_NORM_SD": "gur"}, {"ID": "r.10.1", "FORM": "ki", "SEGM": "ki[place]", "XPOSTAG": "N", "HEAD": "_", "DEPREL": "_", "MISC": "_", "ID_NUM": "65", "BASE": "ki", "SENSE": "place", "MORPH2": "N1=STEM", "EPOS": "N", "POS": "N", "FORM_ATF": "ki", "FORM_NORM": "ki", "FORM_NORM_U": "ki", "FORM_NORM_SD": "ki", "BASE_NORM": "ki", "BASE_NORM_BD": "ki", "BASE_NORM_U": "ki", "BASE_NORM_SD": "ki"}, {"ID": "r.10.2", "FORM": "ka-guru7-ta", "SEGM": "Kaguru[1][-ak]-ta", "XPOSTAG": "PN.GEN.ABL", "HEAD": "_", "DEPREL": "_", "MISC": "_", "ID_NUM": "66", "BASE": "kaguru", "SENSE": "1", "MORPH2": "N1=NAME.N5=GEN.N5=ABL", "EPOS": "PN", "POS": "N", "FORM_ATF": "ka-guru7-ta", "FORM_NORM": "kaguruta", "FORM_NORM_U": "kagur\u1b5fta", "FORM_NORM_SD": "ka", "BASE_NORM": "_", "BASE_NORM_U": "_", "BASE_NORM_SD": "_", "BASE_NORM_BD": "_"}, {"ID": "r.11.1", "FORM": "kiszib3", "SEGM": "kiszib[seal]", "XPOSTAG": "N", "HEAD": "kiszib[seal]", "DEPREL": "N", "MISC": "_", "ID_NUM": "67", "BASE": "kicib", "SENSE": "seal", "MORPH2": "N1=STEM", "EPOS": "N", "POS": "N", "FORM_ATF": "kicib3", "FORM_NORM": "kicib", "FORM_NORM_U": "kic\u138bb", "FORM_NORM_SD": "kicib", "BASE_NORM": "kicib", "BASE_NORM_BD": "kicib", "BASE_NORM_U": "kicib", "BASE_NORM_SD": "kicib"}, {"ID": "r.11.2", "FORM": "i7-pa-e3", "SEGM": "Ipa'e[1][-ak]", "XPOSTAG": "PN.GEN", "HEAD": "_", "DEPREL": "_", "MISC": "_", "ID_NUM": "68", "BASE": "ipa'e", "SENSE": "1", "MORPH2": "N1=NAME.N5=GEN", "EPOS": "PN", "POS": "N", "FORM_ATF": "i7-pa-e3", "FORM_NORM": "ipae", "FORM_NORM_U": "\u138fpa\u0bbb", "FORM_NORM_SD": "i", "BASE_NORM": "_", "BASE_NORM_U": "_", "BASE_NORM_SD": "_", "BASE_NORM_BD": "_"}, {"ID": "r.12.1", "FORM": "mu", "SEGM": "mu[year]", "XPOSTAG": "N", "HEAD": "mu[name]", "DEPREL": "N", "MISC": "mu[year]", "ID_NUM": "69", "BASE": "mu", "SENSE": "year", "MORPH2": "N1=STEM", "EPOS": "N", "POS": "N", "FORM_ATF": "mu", "FORM_NORM": "mu", "FORM_NORM_U": "mu", "FORM_NORM_SD": "mu", "BASE_NORM": "mu", "BASE_NORM_BD": "mu", "BASE_NORM_U": "mu", "BASE_NORM_SD": "mu"}, {"ID": "r.12.2", "FORM": "si-ma-num2{ki}", "SEGM": "Simanum[1][-\u00f8]", "XPOSTAG": "SN.ABS", "HEAD": "_", "DEPREL": "_", "MISC": "_", "ID_NUM": "70", "BASE": "simanum", "SENSE": "1", "MORPH2": "N1=NAME.N5=ABS", "EPOS": "SN", "POS": "N", "FORM_ATF": "si-ma-num2{ki}", "FORM_NORM": "simanum", "FORM_NORM_U": "siman\u1b5am", "FORM_NORM_SD": "siki", "BASE_NORM": "_", "BASE_NORM_U": "_", "BASE_NORM_SD": "_", "BASE_NORM_BD": "_"}, {"ID": "r.12.3", "FORM": "ba-hul", "SEGM": "ba-hulu[destroy][-\u00f8]", "XPOSTAG": "MID.V.3-SG-S", "HEAD": "ba-hulu[bad][-\u00f8][-\u00f8]", "DEPREL": "MID.V.3-SG-S.ABS", "MISC": "_", "ID_NUM": "71", "BASE": "hulu", "SENSE": "destroy", "MORPH2": "V5=MID.V12=STEM.V14=3-SG-S", "EPOS": "V", "POS": "V", "FORM_ATF": "ba-hul", "FORM_NORM": "bahul", "FORM_NORM_U": "bahul", "FORM_NORM_SD": "ba", "BASE_NORM": "hulu", "BASE_NORM_BD": "hulu", "BASE_NORM_U": "hulu", "BASE_NORM_SD": "hulu"}, {"ID": "l.1.1", "FORM": "6(asz)", "SEGM": "6(asz)[one]", "XPOSTAG": "NU", "HEAD": "_", "DEPREL": "_", "MISC": "_", "ID_NUM": "72", "BASE": "6(ac)", "SENSE": "one", "MORPH2": "N1=STEM", "EPOS": "NU", "POS": "NU", "FORM_ATF": "6(ac)", "FORM_NORM": "ac", "FORM_NORM_U": "ac", "FORM_NORM_SD": "ac", "BASE_NORM": "ac", "BASE_NORM_BD": "ac", "BASE_NORM_U": "ac", "BASE_NORM_SD": "ac"}, {"ID": "l.1.2", "FORM": "x", "SEGM": "_", "XPOSTAG": "_", "HEAD": "_", "DEPREL": "_", "MISC": "_", "ID_NUM": "73", "SENSE": "_", "BASE": "_", "EPOS": "_", "POS": "_", "FORM_ATF": "_", "FORM_NORM": "_", "FORM_NORM_U": "_", "FORM_NORM_SD": "_", "BASE_NORM": "_", "BASE_NORM_U": "_", "BASE_NORM_SD": "_", "BASE_NORM_BD": "_"}, {"ID": "l.1.3", "FORM": "3(barig)", "SEGM": "3(bariga)[unit]", "XPOSTAG": "N", "HEAD": "_", "DEPREL": "_", "MISC": "_", "ID_NUM": "74", "BASE": "3(bariga)", "SENSE": "unit", "MORPH2": "N1=STEM", "EPOS": "N", "POS": "N", "FORM_ATF": "3(barig)", "FORM_NORM": "3(barig)", "FORM_NORM_U": "3(barig)", "FORM_NORM_SD": "3(barig)", "BASE_NORM": "3(bariga)", "BASE_NORM_BD": "3(bariga)", "BASE_NORM_U": "3(bariga)", "BASE_NORM_SD": "3(bariga)"}, {"ID": "l.1.4", "FORM": "3(u)", "SEGM": "3(u)[ten]", "XPOSTAG": "NU", "HEAD": "_", "DEPREL": "_", "MISC": "_", "ID_NUM": "75", "BASE": "3(u)", "SENSE": "ten", "MORPH2": "N1=STEM", "EPOS": "NU", "POS": "NU", "FORM_ATF": "3(u)", "FORM_NORM": "u", "FORM_NORM_U": "u", "FORM_NORM_SD": "u", "BASE_NORM": "u", "BASE_NORM_BD": "u", "BASE_NORM_U": "u", "BASE_NORM_SD": "u"}, {"ID": "s1.1.1", "FORM": "i7-pa-e3", "SEGM": "Ipa'e[1]", "XPOSTAG": "PN", "HEAD": "_", "DEPREL": "_", "MISC": "_", "ID_NUM": "76", "BASE": "ipa'e", "SENSE": "1", "MORPH2": "N1=NAME", "EPOS": "PN", "POS": "N", "FORM_ATF": "i7-pa-e3", "FORM_NORM": "ipae", "FORM_NORM_U": "\u138fpa\u0bbb", "FORM_NORM_SD": "i", "BASE_NORM": "_", "BASE_NORM_U": "_", "BASE_NORM_SD": "_", "BASE_NORM_BD": "_"}, {"ID": "s1.2.1", "FORM": "dumu", "SEGM": "dumu[child]", "XPOSTAG": "N", "HEAD": "_", "DEPREL": "_", "MISC": "_", "ID_NUM": "77", "BASE": "dumu", "SENSE": "child", "MORPH2": "N1=STEM", "EPOS": "N", "POS": "N", "FORM_ATF": "dumu", "FORM_NORM": "dumu", "FORM_NORM_U": "dumu", "FORM_NORM_SD": "dumu", "BASE_NORM": "dumu", "BASE_NORM_BD": "dumu", "BASE_NORM_U": "dumu", "BASE_NORM_SD": "dumu"}, {"ID": "s1.2.2", "FORM": "lugal-uszurx(|LAL2.TUG2|)", "SEGM": "Lugaluszur[1][-ak]", "XPOSTAG": "PN.GEN", "HEAD": "_", "DEPREL": "_", "MISC": "_", "ID_NUM": "78", "BASE": "lugalucur", "SENSE": "1", "MORPH2": "N1=NAME.N5=GEN", "EPOS": "PN", "POS": "N", "FORM_ATF": "_", "FORM_NORM": "_", "FORM_NORM_U": "_", "FORM_NORM_SD": "_", "BASE_NORM": "_", "BASE_NORM_U": "_", "BASE_NORM_SD": "_", "BASE_NORM_BD": "_"}], "info_dict": {"title": "new_text=P102280", "legend": ["ID", "FORM", "SEGM", "XPOSTAG", "HEAD", "DEPREL", "MISC"]}, "corpus": "cdli", "convention": "ORACC", "info_lst": ["#new_text=P102280", "# ID\tFORM\tSEGM\tXPOSTAG\tHEAD\tDEPREL\tMISC"], "filename": "P102280.conll"}